anothertestproject/__init__.py
anothertestproject/module.py
anothertestproject/binaries/annoter.dll
anothertestproject/binaries/connector.exe
anothertestproject-0.1.7.dist-info/licenses/LICENSE
anothertestproject-0.1.7.dist-info/METADATA
anothertestproject-0.1.7.dist-info/WHEEL
anothertestproject-0.1.7.dist-info/top_level.txt
anothertestproject-0.1.7.dist-info/RECORD
