Metadata-Version: 2.4
Name: anothertestproject
Version: 0.1.7
Summary: Описание вашей библиотеки
Author: Ваше Имя
Author-email: your@email.com
Classifier: Programming Language :: Python :: 3
Classifier: License :: OSI Approved :: MIT License
Requires-Python: >=3.7
License-File: LICENSE
Dynamic: author
Dynamic: author-email
Dynamic: classifier
Dynamic: description-content-type
Dynamic: license-file
Dynamic: requires-python
Dynamic: summary
